cert_issuer/__init__.py
cert_issuer/__main__.py
cert_issuer/certificate_handlers.py
cert_issuer/config.py
cert_issuer/digests.py
cert_issuer/errors.py
cert_issuer/helpers.py
cert_issuer/issue_certificates.py
cert_issuer/issuer.py
cert_issuer/merkle_tree_generator.py
cert_issuer/normalization_handler.py
cert_issuer/proof_handler.py
cert_issuer/signer.py
cert_issuer/utils.py
cert_issuer/blockchain_handlers/__init__.py
cert_issuer/blockchain_handlers/bitcoin/__init__.py
cert_issuer/blockchain_handlers/bitcoin/connectors.py
cert_issuer/blockchain_handlers/bitcoin/signer.py
cert_issuer/blockchain_handlers/bitcoin/transaction_handlers.py
cert_issuer/blockchain_handlers/bitcoin/tx_utils.py
cert_issuer/blockchain_handlers/ethereum/__init__.py
cert_issuer/blockchain_handlers/ethereum/connectors.py
cert_issuer/blockchain_handlers/ethereum/signer.py
cert_issuer/blockchain_handlers/ethereum/transaction_handlers.py
cert_issuer/blockchain_handlers/ethereum/tx_utils.py
cert_issuer/models/__init__.py
cert_issuer/models/metadata.py
cert_issuer/models/verifiable_credential.py
cert_issuer/proof_suites/__init__.py
cert_issuer/proof_suites/merkle_proof_2019.py
cert_issuer-3.13.0.dist-info/licenses/LICENSE
tests/__init__.py
tests/test_certificate_handler.py
tests/test_connectors.py
tests/test_merkle_tree_generator.py
tests/test_proof_handler.py
tests/test_signer.py
tests/test_tx_utils.py
cert_issuer-3.13.0.dist-info/METADATA
cert_issuer-3.13.0.dist-info/WHEEL
cert_issuer-3.13.0.dist-info/entry_points.txt
cert_issuer-3.13.0.dist-info/top_level.txt
cert_issuer-3.13.0.dist-info/RECORD
