Metadata-Version: 2.4
Name: cert-issuer
Version: 3.13.0
Summary: Issues blockchain certificates using the Bitcoin blockchain
Home-page: https://github.com/blockchain-certificates/cert-issuer
Author: Blockcerts
Author-email: info@blockcerts.org
License: MIT
License-File: LICENSE
Requires-Dist: cert-core>=3.0.0
Requires-Dist: cert-schema>=3.10.0
Requires-Dist: blockcerts-merkletools>=1.0.4
Requires-Dist: configargparse==0.13.0
Requires-Dist: glob2==0.6
Requires-Dist: mock==2.0.0
Requires-Dist: requests[security]>=2.18.4
Requires-Dist: pycoin==0.92.20241201
Requires-Dist: pyld==2.0.3
Requires-Dist: safe-pysha3>=1.0.2
Requires-Dist: python-bitcoinlib>=0.10.1
Requires-Dist: tox>=3.0.0
Requires-Dist: jsonschema>=4.0.0
Requires-Dist: lds-merkle-proof-2019>=0.1.0
Requires-Dist: connexion==3.2.0
Requires-Dist: setuptools>=75.8.0
Dynamic: author
Dynamic: author-email
Dynamic: description
Dynamic: description-content-type
Dynamic: home-page
Dynamic: license
Dynamic: license-file
Dynamic: requires-dist
Dynamic: summary
